./.gitignore
./PKG-INFO
./README.md
./pyproject.toml
./vision_agents/plugins/inworld/__init__.py
./vision_agents/plugins/inworld/tts.py
vision_agents/plugins/inworld/__init__.py
vision_agents/plugins/inworld/tts.py
vision_agents_plugins_inworld-0.2.10.dist-info/METADATA
vision_agents_plugins_inworld-0.2.10.dist-info/WHEEL
vision_agents_plugins_inworld-0.2.10.dist-info/RECORD
