Metadata-Version: 2.4
Name: vision-agents-plugins-inworld
Version: 0.2.10
Summary: Inworld AI TTS integration for Vision Agents
Project-URL: Documentation, https://visionagents.ai/
Project-URL: Website, https://visionagents.ai/
Project-URL: Source, https://github.com/GetStream/Vision-Agents
License-Expression: MIT
Keywords: AI,TTS,agents,inworld,text-to-speech,voice agents
Requires-Python: >=3.10
Requires-Dist: av>=10.0.0
Requires-Dist: httpx>=0.27.0
Requires-Dist: vision-agents
